{
  "proof_hash": "6432a8f0ddf1f1dd738c5e31821be715814e94fcb54718d5adfe68975ac66f6e",
  "timestamp": "2025-12-01T18:31:05.162290",
  "result": {
    "symbol": "TSLA",
    "timestamp": "2025-12-01T18:31:05.156281",
    "window_hash": "2ed98d6cf0c862ad",
    "quantrascore": 32.549747182336844,
    "score_bucket": "low",
    "regime": "range_bound",
    "risk_tier": "high",
    "entropy_state": "stable",
    "suppression_state": "none",
    "drift_state": "critical",
    "microtraits": {
      "wick_ratio": 0.41161898617721726,
      "body_ratio": 0.46838101382278274,
      "bullish_pct_last20": 0.45,
      "compression_score": 0.0,
      "noise_score": 0.5625,
      "strength_slope": 0.014115273954919393,
      "range_density": 0.17025238362310663,
      "volume_intensity": 0.9302917766085554,
      "trend_consistency": -0.02040816326530612,
      "volatility_ratio": 0.48929450274055997
    },
    "entropy_metrics": {
      "price_entropy": 0.8424216951314378,
      "volume_entropy": 0.7572556605594731,
      "combined_entropy": 0.8168718847598484,
      "entropy_state": "stable",
      "entropy_floor": 0.722622978699136
    },
    "suppression_metrics": {
      "suppression_level": 0.014654553289284238,
      "suppression_state": "none",
      "coil_factor": 0.029229876535211263,
      "breakout_probability": 0.1,
      "is_suppressed": false,
      "suppression_score": 0.014654553289284238
    },
    "drift_metrics": {
      "drift_magnitude": 0.11419217759348402,
      "drift_direction": -1.0,
      "drift_state": "critical",
      "mean_reversion_pressure": 0.05709608879674201
    },
    "continuation_metrics": {
      "continuation_probability": 0.0,
      "momentum_strength": 0.0,
      "exhaustion_signal": true,
      "reversal_risk": 0.4
    },
    "volume_metrics": {
      "volume_spike_detected": false,
      "spike_magnitude": 0.8857960559209885,
      "volume_trend": "stable",
      "relative_volume": 0.8857960559209885
    },
    "protocol_results": [
      {
        "protocol_id": "T01",
        "fired": false,
        "confidence": 0.3,
        "signal_type": "trend_unclear",
        "details": {
          "current_price": 402.9,
          "sma20": 404.7354999999999,
          "sma50": 403.85360000000003,
          "trend_consistency": -0.02040816326530612
        }
      },
      {
        "protocol_id": "T02",
        "fired": true,
        "confidence": 0.44812578929061797,
        "signal_type": "moderate_trend",
        "details": {
          "adx": 29.665427509293917,
          "combined_strength": 0.24812578929061796,
          "body_consistency": 0.46838101382278274
        }
      },
      {
        "protocol_id": "T03",
        "fired": false,
        "confidence": 0.3,
        "signal_type": "momentum_diverging",
        "details": {
          "roc_5": -0.547985781990528,
          "roc_10": -1.9731880002919673,
          "roc_20": 0.22138752767343756,
          "momentum_aligned": false
        }
      },
      {
        "protocol_id": "T04",
        "fired": false,
        "confidence": 0.2,
        "signal_type": "no_clear_channel",
        "details": {
          "channel_direction": "ascending",
          "position_in_channel": -0.21372972972974405,
          "channel_width": 3.9642857142856656,
          "parallel_score": 0.40268852714384673
        }
      },
      {
        "protocol_id": "T05",
        "fired": false,
        "confidence": 0.1,
        "signal_type": "no_crossover",
        "details": {
          "current_fast_ma": 405.018,
          "current_slow_ma": 404.7354999999999,
          "bars_since_cross": 0
        }
      },
      {
        "protocol_id": "T06",
        "fired": false,
        "confidence": 0.1,
        "signal_type": "no_expansion",
        "details": {
          "expansion_ratio": 1.058343634116196,
          "was_compressed": false,
          "compression_score": 0.0
        }
      },
      {
        "protocol_id": "T07",
        "fired": false,
        "confidence": 0.2,
        "signal_type": "no_squeeze",
        "details": {
          "current_bb_width": 0.032349856766601286,
          "squeeze_ratio": 1.169419501288954,
          "near_minimum": false
        }
      },
      {
        "protocol_id": "T08",
        "fired": false,
        "confidence": 0.15,
        "signal_type": "no_contraction",
        "details": {
          "current_atr": 3.7146428571428567,
          "average_atr": 3.192453917050689,
          "contraction_ratio": 1.1635697659731876,
          "atr_declining": false
        }
      },
      {
        "protocol_id": "T09",
        "fired": true,
        "confidence": 0.45,
        "signal_type": "moderate_range_compression",
        "details": {
          "narrowing_bars": 4,
          "compression_pct": 0.23852721451440606,
          "microtraits_compression": 0.0
        }
      },
      {
        "protocol_id": "T10",
        "fired": false,
        "confidence": 0.2,
        "signal_type": "vol_stable",
        "details": {
          "realized_vol": 0.10260060023363511,
          "vol_ratio": 0.8748580444782268,
          "vol_skew": -1.037919623954398
        }
      },
      {
        "protocol_id": "T11",
        "fired": false,
        "confidence": 0.15,
        "signal_type": "no_bullish_continuation",
        "details": {
          "in_uptrend": false,
          "recent_pullback": false,
          "bullish_pct": 0.45
        }
      },
      {
        "protocol_id": "T12",
        "fired": false,
        "confidence": 0.15,
        "signal_type": "no_bearish_continuation",
        "details": {
          "in_downtrend": true,
          "recent_bounce": false,
          "bearish_pct": 0.55
        }
      },
      {
        "protocol_id": "T13",
        "fired": false,
        "confidence": 0.1,
        "signal_type": "no_flag",
        "details": {
          "pole_move_pct": -0.7595437789158548,
          "flag_slope": -0.3120714285714318,
          "flag_tight": true
        }
      },
      {
        "protocol_id": "T14",
        "fired": false,
        "confidence": 0.1,
        "signal_type": "no_pennant",
        "details": {
          "converging": false,
          "range_contraction": 0,
          "prior_move_pct": -0.7595437789158548
        }
      },
      {
        "protocol_id": "T15",
        "fired": false,
        "confidence": 0.1,
        "signal_type": "no_wedge",
        "details": {
          "high_slope": 0.1728759398496201,
          "low_slope": 0.04358270676691611,
          "both_up": true,
          "both_down": false
        }
      },
      {
        "protocol_id": "T16",
        "fired": true,
        "confidence": 0.6,
        "signal_type": "double_bottom_forming",
        "details": {
          "low1": 399.53,
          "low2": 398.63,
          "similar_lows": true,
          "neckline": 409.06
        }
      },
      {
        "protocol_id": "T17",
        "fired": false,
        "confidence": 0.1,
        "signal_type": "no_double_top",
        "details": {
          "high1": 406.5,
          "high2": 411.67,
          "similar_highs": true,
          "neckline": 400.13
        }
      },
      {
        "protocol_id": "T18",
        "fired": false,
        "confidence": 0.1,
        "signal_type": "no_hs",
        "details": {
          "left_shoulder": 408.57,
          "head": 406.5,
          "right_shoulder": 411.67,
          "neckline": 402.185
        }
      },
      {
        "protocol_id": "T19",
        "fired": false,
        "confidence": 0.1,
        "signal_type": "no_ihs",
        "details": {
          "left_shoulder": 396.05,
          "head": 399.53,
          "right_shoulder": 398.63,
          "neckline": 407.55
        }
      },
      {
        "protocol_id": "T20",
        "fired": false,
        "confidence": 0.1,
        "signal_type": "no_climax",
        "details": {
          "volume_zscore": -0.15884354332818046,
          "relative_volume": 0.8951710157763155,
          "wide_range": false,
          "reversal_wick": true
        }
      },
      {
        "protocol_id": "T21",
        "fired": false,
        "confidence": 0.3,
        "signal_type": "volatility_stable",
        "details": {
          "atr_short": 2.8540000000000076,
          "atr_long": 2.7360000000000015,
          "expansion_ratio": 1.0431286549707623,
          "range_expansion": 0.3295036764705865
        }
      },
      {
        "protocol_id": "T22",
        "fired": false,
        "confidence": 0.2,
        "signal_type": "no_contraction",
        "details": {
          "atr_recent": 2.8540000000000076,
          "atr_prior": 2.696666666666666,
          "contraction_ratio": 1.058343634116196,
          "compression_score": 0.0
        }
      },
      {
        "protocol_id": "T23",
        "fired": false,
        "confidence": 0.2,
        "signal_type": "no_squeeze",
        "details": {
          "band_width": 0.03234985676660126,
          "squeeze_ratio": 1.155000703745731,
          "upper_band": 411.28206772667926,
          "lower_band": 398.1889322733205
        }
      },
      {
        "protocol_id": "T24",
        "fired": true,
        "confidence": 0.6,
        "signal_type": "moderate_breakout",
        "details": {
          "atr14": 3.7146428571428567,
          "last_move": 0.029999999999972715,
          "atr_multiple": 0.008076146524365313,
          "range_atr": 2.0513412171906564
        }
      },
      {
        "protocol_id": "T25",
        "fired": false,
        "confidence": 0.3,
        "signal_type": "within_keltner",
        "details": {
          "upper_keltner": 411.0697105263157,
          "lower_keltner": 398.4012894736841,
          "ema20": 404.7354999999999,
          "atr": 3.1671052631578953,
          "current_price": 402.9
        }
      },
      {
        "protocol_id": "T26",
        "fired": true,
        "confidence": 0.85,
        "signal_type": "high_volatility",
        "details": {
          "vol_5d": 0.0631560832194674,
          "vol_20d": 0.11267527107118087,
          "vol_50d": 0.10260060023363511,
          "vol_percentile": 89.65517241379311
        }
      },
      {
        "protocol_id": "T27",
        "fired": false,
        "confidence": 0.4,
        "signal_type": "symmetric_volatility",
        "details": {
          "upside_vol": 0.004372598986490962,
          "downside_vol": 0.004180730749628845,
          "skew_ratio": 1.0458934689537591,
          "up_count": 24,
          "down_count": 25
        }
      },
      {
        "protocol_id": "T28",
        "fired": false,
        "confidence": 0.3,
        "signal_type": "normal_ranges",
        "details": {
          "avg_range": 2.7360000000000015,
          "recent_range": 2.8540000000000076,
          "range_ratio": 1.0431286549707623,
          "avg_range_pct": 0.6745907745909945,
          "hl_consistency": 0.33763221198165005
        }
      },
      {
        "protocol_id": "T29",
        "fired": true,
        "confidence": 0.6,
        "signal_type": "consistent_gap_direction",
        "details": {
          "last_gap_pct": 0.0,
          "avg_gap_size": 0.046724715619440325,
          "hist_avg_gap": 0.11690739720241483,
          "gap_direction_consistency": 0.0
        }
      },
      {
        "protocol_id": "T30",
        "fired": true,
        "confidence": 0.6,
        "signal_type": "vol_moderately_extended",
        "details": {
          "vol_5d": 0.0631560832194674,
          "vol_20d": 0.11267527107118087,
          "vol_50d": 0.10260060023363511,
          "vol_ratio_short": 0.6155527655359975,
          "z_score": -1.845918010917553,
          "reversion_direction": "expect_normalization"
        }
      },
      {
        "protocol_id": "T31",
        "fired": false,
        "confidence": 0.3,
        "signal_type": "neutral_momentum",
        "details": {
          "rsi": 45.23740168948434,
          "rsi_trend": -5.820433221787091,
          "avg_gain": 1.1092857142857082,
          "avg_loss": 1.3428571428571396
        }
      },
      {
        "protocol_id": "T32",
        "fired": true,
        "confidence": 0.75,
        "signal_type": "strong_momentum",
        "details": {
          "macd": -0.1453131555142022,
          "signal": 0.4089301938857301,
          "histogram": -0.5542433493999324,
          "macd_slope": -0.15369681222654208
        }
      },
      {
        "protocol_id": "T33",
        "fired": false,
        "confidence": 0.3,
        "signal_type": "neutral",
        "details": {
          "stoch_k": 32.745398773005945,
          "stoch_d": 32.09014154202219,
          "lowest_low": 398.63,
          "highest_high": 411.67
        }
      },
      {
        "protocol_id": "T34",
        "fired": true,
        "confidence": 0.75,
        "signal_type": "strong_momentum",
        "details": {
          "roc_10": -1.9731880002919673,
          "roc_5": -0.547985781990528,
          "roc_1": 0.007446570854114903,
          "roc_zscore": -1.653437426941437,
          "roc_acceleration": 0.8772164363109112
        }
      },
      {
        "protocol_id": "T35",
        "fired": false,
        "confidence": 0.3,
        "signal_type": "no_divergence",
        "details": {
          "rsi_current": 45.23740168948434,
          "rsi_prev": 53.09264666843648,
          "price_change_pct": -0.8050816160720975,
          "divergence_strength": 0.019557118176883215
        }
      },
      {
        "protocol_id": "T36",
        "fired": true,
        "confidence": 0.65,
        "signal_type": "trending",
        "details": {
          "adx": 29.665427509293917,
          "plus_di": 18.190558600134565,
          "minus_di": 33.535236996442755,
          "dx": 29.665427509293917
        }
      },
      {
        "protocol_id": "T37",
        "fired": false,
        "confidence": 0.3,
        "signal_type": "neutral",
        "details": {
          "williams_r": -67.25460122699405,
          "wr_trend": 0.4391666085288648,
          "highest_high": 411.67,
          "lowest_low": 398.63
        }
      },
      {
        "protocol_id": "T38",
        "fired": false,
        "confidence": 0.3,
        "signal_type": "neutral",
        "details": {
          "cci": -40.716187740690394,
          "cci_trend": -4.0518895071840575,
          "typical_price": 403.125,
          "sma": 404.7126666666666
        }
      },
      {
        "protocol_id": "T39",
        "fired": false,
        "confidence": 0.3,
        "signal_type": "no_exhaustion",
        "details": {
          "price_trend_pct": -1.3008010582788276,
          "momentum_deceleration": -0.2539670300802258,
          "volume_decline_pct": 15.98206617235701,
          "exhaustion_score": 2.601288012537447
        }
      },
      {
        "protocol_id": "T40",
        "fired": true,
        "confidence": 0.5,
        "signal_type": "partial_alignment",
        "details": {
          "mom_5": -0.7794318643566966,
          "mom_10": -1.3008010582788276,
          "mom_20": 0.44375747905862895,
          "mom_50": -1.4962593516209488,
          "alignment_score": 0.25,
          "avg_momentum": -0.7831836987994609
        }
      },
      {
        "protocol_id": "T41",
        "fired": false,
        "confidence": 0.3,
        "signal_type": "normal_volume",
        "details": {
          "current_volume": 28719.0,
          "avg_volume_20": 32236.55,
          "volume_ratio": 0.8908831745332549,
          "volume_zscore": -0.14056299598995456,
          "price_change_pct": 0.007446570854114903
        }
      },
      {
        "protocol_id": "T42",
        "fired": true,
        "confidence": 0.85,
        "signal_type": "bullish_divergence",
        "details": {
          "obv_current": -140266.0,
          "obv_sma20": -193809.95,
          "obv_trend": 31503.0,
          "obv_slope": -0.020371985635439314
        }
      },
      {
        "protocol_id": "T43",
        "fired": false,
        "confidence": 0.3,
        "signal_type": "no_confirmation",
        "details": {
          "up_volume": 779508.0,
          "down_volume": 919774.0,
          "volume_ratio": 0.8474994944410257,
          "recent_price_trend": -1.3008010582788276,
          "recent_volume_trend": -15.98206617235701
        }
      },
      {
        "protocol_id": "T44",
        "fired": true,
        "confidence": 0.85,
        "signal_type": "bullish_divergence",
        "details": {
          "ad_current": -121173.3624483741,
          "ad_sma10": -157428.2494209529,
          "ad_sma20": -180269.45656194276,
          "ad_trend": 63450.081335266004
        }
      },
      {
        "protocol_id": "T45",
        "fired": false,
        "confidence": 0.3,
        "signal_type": "neutral",
        "details": {
          "mfi": 54.144966915540756,
          "mfi_trend": -0.416817907162752,
          "positive_mf": 107609963.21333331,
          "negative_mf": 91134203.315
        }
      },
      {
        "protocol_id": "T46",
        "fired": true,
        "confidence": 0.6,
        "signal_type": "at_vwap",
        "details": {
          "current_price": 402.9,
          "vwap": 403.4631325926028,
          "deviation_pct": -0.13957473362787676,
          "above_vwap_streak": 0,
          "below_vwap_streak": 4
        }
      },
      {
        "protocol_id": "T47",
        "fired": false,
        "confidence": 0.3,
        "signal_type": "neutral",
        "details": {
          "cmf": -0.01549351023567301,
          "cmf_trend": 0.06843963774602582
        }
      },
      {
        "protocol_id": "T48",
        "fired": true,
        "confidence": 0.85,
        "signal_type": "at_poc",
        "details": {
          "current_price": 402.9,
          "poc_price": 403.20074999999997,
          "distance_to_poc_pct": 0.0746463142218897,
          "current_volume_node": 215104.0,
          "avg_volume_node": 90226.25
        }
      },
      {
        "protocol_id": "T49",
        "fired": false,
        "confidence": 0.3,
        "signal_type": "neutral",
        "details": {
          "fi_13_ema": 21514.55884615375,
          "fi_normalized": 0.15569798654800232,
          "positive_streak": 1,
          "negative_streak": 0
        }
      },
      {
        "protocol_id": "T50",
        "fired": false,
        "confidence": 0.3,
        "signal_type": "no_climax",
        "details": {
          "volume_zscore": -0.14056299598995456,
          "range_expansion": 0.8351608187134382,
          "price_change_pct": 0.007446570854114903,
          "climax_score": 0.18175606178987713,
          "recent_trend_pct": -1.3008010582788276
        }
      },
      {
        "protocol_id": "T51",
        "fired": true,
        "confidence": 0.75,
        "signal_type": "doji",
        "details": {
          "patterns_detected": [
            "doji"
          ],
          "body_size": 0.029999999999972715,
          "upper_shadow": 1.4800000000000182,
          "lower_shadow": 0.7749999999999773,
          "is_bullish": true
        }
      },
      {
        "protocol_id": "T52",
        "fired": true,
        "confidence": 0.8,
        "signal_type": "double_top",
        "details": {
          "local_highs_count": 5,
          "local_lows_count": 8,
          "pattern_price": 397.63
        }
      },
      {
        "protocol_id": "T53",
        "fired": true,
        "confidence": 0.85,
        "signal_type": "head_and_shoulders",
        "details": {
          "neckline": 398.79999999999995,
          "local_highs_count": 5,
          "local_lows_count": 6
        }
      },
      {
        "protocol_id": "T54",
        "fired": false,
        "confidence": 0.2,
        "signal_type": "no_triangle",
        "details": {
          "high_slope": 0.1728759398496201,
          "low_slope": 0.04358270676691611,
          "trendline_quality": 0.044390977465364245,
          "range_contraction": false
        }
      },
      {
        "protocol_id": "T55",
        "fired": false,
        "confidence": 0.2,
        "signal_type": "no_pattern",
        "details": {
          "pole_move_pct": 0.4898686261411757,
          "high_slope": -0.7390606060605848,
          "low_slope": -0.6613333333333441,
          "consolidation": false
        }
      },
      {
        "protocol_id": "T56",
        "fired": false,
        "confidence": 0.2,
        "signal_type": "no_wedge",
        "details": {
          "high_slope": 0.1728759398496201,
          "low_slope": 0.04358270676691611,
          "both_rising": true,
          "both_falling": false,
          "narrowing": false
        }
      },
      {
        "protocol_id": "T57",
        "fired": false,
        "confidence": 0.2,
        "signal_type": "no_cup",
        "details": {
          "left_rim": 409.02,
          "cup_bottom": 400.13,
          "right_rim": 411.01,
          "cup_depth_pct": 2.1734878490049354,
          "handle_pullback_pct": 2.075375295004981
        }
      },
      {
        "protocol_id": "T58",
        "fired": true,
        "confidence": 0.85,
        "signal_type": "island_bottom_reversal",
        "details": {
          "gap_count": 9,
          "gap1_idx": 1,
          "gap2_idx": 3
        }
      },
      {
        "protocol_id": "T59",
        "fired": false,
        "confidence": 0.2,
        "signal_type": "no_pattern",
        "details": {
          "curvature_a": -0.0019015291512075331,
          "r_squared": 0.0622597009693826,
          "vertex_x": 34.193171238346686,
          "depth_pct": 1.0316050704362307
        }
      },
      {
        "protocol_id": "T60",
        "fired": false,
        "confidence": 0.2,
        "signal_type": "no_pattern",
        "details": {
          "local_highs_count": 5,
          "local_lows_count": 6
        }
      },
      {
        "protocol_id": "T61",
        "fired": true,
        "confidence": 0.9,
        "signal_type": "at_support",
        "details": {
          "current_price": 402.9,
          "nearest_support": 399.78375,
          "support_touches": 7,
          "distance_pct": 0.7734549516008885,
          "total_support_levels": 1
        }
      },
      {
        "protocol_id": "T62",
        "fired": true,
        "confidence": 0.9,
        "signal_type": "at_resistance",
        "details": {
          "current_price": 402.9,
          "nearest_resistance": 408.8,
          "resistance_touches": 5,
          "distance_pct": 1.4643832216430963,
          "total_resistance_levels": 1
        }
      },
      {
        "protocol_id": "T63",
        "fired": true,
        "confidence": 0.8,
        "signal_type": "at_sma50",
        "details": {
          "current_price": 402.9,
          "sma20": 404.7354999999999,
          "sma50": 403.85360000000003,
          "ema20": 404.30299888835464,
          "nearest_ma_distance_pct": 0.2366840407049023
        }
      },
      {
        "protocol_id": "T64",
        "fired": true,
        "confidence": 0.8,
        "signal_type": "at_50_retracement",
        "details": {
          "current_price": 402.9,
          "swing_high": 411.67,
          "swing_low": 393.84,
          "nearest_fib_level": "0.500",
          "nearest_fib_price": 402.755,
          "distance_pct": 0.03598907917596968
        }
      },
      {
        "protocol_id": "T65",
        "fired": true,
        "confidence": 0.8,
        "signal_type": "at_pivot",
        "details": {
          "current_price": 402.9,
          "pivot": 401.58,
          "r1": 404.53,
          "r2": 406.19,
          "r3": 409.14,
          "s1": 399.91999999999996,
          "s2": 396.96999999999997,
          "s3": 395.30999999999995,
          "nearest_level": "Pivot"
        }
      },
      {
        "protocol_id": "T66",
        "fired": true,
        "confidence": 0.7,
        "signal_type": "near_major_level",
        "details": {
          "current_price": 402.9,
          "major_round": 400.0,
          "minor_round": 405.0,
          "distance_major_pct": 0.7197815835194781,
          "recent_crosses": 1
        }
      },
      {
        "protocol_id": "T67",
        "fired": false,
        "confidence": 0.3,
        "signal_type": "no_breakout",
        "details": {
          "prior_high": 411.67,
          "prior_low": 399.53,
          "current_price": 402.9,
          "volume_confirmation": false,
          "breakout_magnitude_pct": 0.0
        }
      },
      {
        "protocol_id": "T68",
        "fired": true,
        "confidence": 0.55,
        "signal_type": "possible_false_breakout",
        "details": {
          "prior_high": 411.67,
          "prior_low": 399.53,
          "bull_trap": false,
          "bear_trap": true,
          "rejection_wick": false,
          "weak_volume": false
        }
      },
      {
        "protocol_id": "T69",
        "fired": false,
        "confidence": 0.3,
        "signal_type": "no_flip",
        "details": {
          "prior_support": 399.53,
          "prior_resistance": 406.5,
          "current_price": 402.9,
          "support_to_resistance": false,
          "resistance_to_support": false
        }
      },
      {
        "protocol_id": "T70",
        "fired": true,
        "confidence": 0.5,
        "signal_type": "range_midpoint",
        "details": {
          "range_high": 411.67,
          "range_low": 398.63,
          "current_price": 402.9,
          "range_size_pct": 3.2185610267802103,
          "touches_upper": 1,
          "touches_lower": 1
        }
      },
      {
        "protocol_id": "T71",
        "fired": false,
        "confidence": 0.3,
        "signal_type": "no_clear_trend",
        "details": {
          "sma20": 404.7354999999999,
          "sma50": 403.85360000000003,
          "trend_strength_score": 0.0,
          "price_distance_sma20": -0.45350605518910775,
          "bullish_aligned": false,
          "bearish_aligned": false
        }
      },
      {
        "protocol_id": "T72",
        "fired": true,
        "confidence": 0.75,
        "signal_type": "range_bound",
        "details": {
          "volatility": 0.11267527107118087,
          "trend_strength": 0.0003035677909502078,
          "price_range_pct": 3.23653512037727,
          "trend_consistency": 0.5789473684210527,
          "is_trending": false,
          "is_volatile": false,
          "is_ranging": true
        }
      },
      {
        "protocol_id": "T73",
        "fired": false,
        "confidence": 0.0,
        "signal_type": null,
        "details": {
          "reason": "insufficient_data"
        }
      },
      {
        "protocol_id": "T74",
        "fired": false,
        "confidence": 0.3,
        "signal_type": "mid_range",
        "details": {
          "current_price": 402.9,
          "position_20_pct": 32.745398773005945,
          "position_50_pct": 50.813236118900626,
          "high_20": 411.67,
          "low_20": 398.63,
          "high_50": 411.67,
          "low_50": 393.84
        }
      },
      {
        "protocol_id": "T75",
        "fired": true,
        "confidence": 0.75,
        "signal_type": "young_trend",
        "details": {
          "days_in_trend": 4,
          "total_move_pct": -0.7794318643566966,
          "pullback_ratio": 0.5,
          "trend_direction": "down"
        }
      },
      {
        "protocol_id": "T76",
        "fired": true,
        "confidence": 0.7164131120651189,
        "signal_type": "weekly_seasonality_detected",
        "details": {
          "day_spread": 0.721377040217063,
          "monthly_position": 10,
          "cycle_5_avg": -0.10904316700427719,
          "cycle_10_avg": -0.1974398483199413,
          "cycle_20_avg": 0.013571150382058894
        }
      },
      {
        "protocol_id": "T77",
        "fired": false,
        "confidence": 0.35,
        "signal_type": "low_reversion_probability",
        "details": {
          "deviation_sma20_pct": -0.45350605518910775,
          "deviation_sma50_pct": -0.23612517011116188,
          "zscore": -0.6389321607228173,
          "reversion_rate": 0.0,
          "reversion_score": 0.20074976932062735
        }
      },
      {
        "protocol_id": "T78",
        "fired": false,
        "confidence": 0.35,
        "signal_type": "uncertain_continuation",
        "details": {
          "trend_10_pct": -1.9731880002919673,
          "trend_20_pct": 0.22138752767343756,
          "trend_alignment": false,
          "volume_support": false,
          "pullback_depth_pct": 0.10435301132974534,
          "continuation_score": 0.25
        }
      },
      {
        "protocol_id": "T79",
        "fired": true,
        "confidence": 0.6,
        "signal_type": "subdued_risk",
        "details": {
          "vol_5_annualized": 6.3156083219467405,
          "vol_20_annualized": 11.267527107118088,
          "vol_50_annualized": 10.260060023363511,
          "risk_score": 0.1631560832194674,
          "large_moves_count": 0,
          "gap_count": 0
        }
      },
      {
        "protocol_id": "T80",
        "fired": false,
        "confidence": 0.35,
        "signal_type": "neutral_composite",
        "details": {
          "trend_signal": 0,
          "momentum_signal": 0,
          "volatility_signal": 1,
          "volume_signal": 0,
          "bullish_count": 1,
          "bearish_count": 0,
          "alignment_score": 0.25
        }
      }
    ],
    "monster_runner_results": {
      "any_fired": false,
      "protocols_fired": [],
      "monster_score": 0.1,
      "confidence": 10.0,
      "dominant_signal": null,
      "individual_results": {
        "MR01": "MR01Result(protocol_id='MR01', fired=False, compression_score=0.0837, atr_contraction_ratio=0.9039, range_tightness=0.8191, bollinger_squeeze=1.0213, explosion_probability=0.0, direction_bias='bullish', confidence=8.37, notes='No significant compression')",
        "MR02": "MR02Result(protocol_id='MR02', fired=False, volume_anomaly_score=0.0, spike_magnitude=-0.1406, accumulation_signal=0.5734, distribution_signal=0.4266, climax_detected=False, dry_up_detected=False, confidence=0.0, notes='No significant volume anomaly')",
        "MR03": "MR03Result(protocol_id='MR03', fired=False, regime_shift_score=0.0, current_regime='normal', previous_regime='normal', transition_strength=0.0, volatility_expansion=0.0, volatility_contraction=0.0, confidence=0.0, notes='Insufficient data (need 60+ bars)')",
        "MR04": "MR04Result(protocol_id='MR04', fired=False, institutional_score=0.09, large_bar_ratio=0.3, price_volume_divergence=0.0147, stealth_accumulation=0.0, stealth_distribution=0.0, footprint_type='none', confidence=9.0, notes='Large bar ratio: 30.0%')",
        "MR05": "MR05Result(protocol_id='MR05', fired=False, alignment_score=0.0, trend_alignment=0.0, momentum_alignment=0.0, structure_alignment=0.0, timeframe_scores={}, dominant_direction='neutral', confidence=0.0, notes='Insufficient data (need 100+ bars)')",
        "MR06": "MR06Result(protocol_id='MR06', fired=False, breakout_score=0.0, squeeze_depth=0.0, breakout_direction='neutral', band_width=0.0323, price_vs_upper=-0.0204, price_vs_lower=0.0118, confidence=0.0, notes='No breakout detected')",
        "MR07": "MR07Result(protocol_id='MR07', fired=False, explosion_score=0.0, volume_multiple=0.8858, price_change_pct=0.0001, direction='bullish', institutional_signature=False, confidence=0.0, notes='No explosion detected')",
        "MR08": "MR08Result(protocol_id='MR08', fired=False, runner_score=0.1, gap_pct=0.0, gap_direction='neutral', continuation=False, intraday_strength=0.0131, fill_probability=0.3, confidence=10.0, notes='Gap fade risk; Gap unfilled')",
        "MR09": "MR09Result(protocol_id='MR09', fired=False, vwap_score=0.0, vwap_deviation=0.0014, breakout_direction='neutral', volume_confirmation=False, price_vs_vwap=-0.0014, confidence=0.0, notes='No VWAP breakout detected')",
        "MR10": "MR10Result(protocol_id='MR10', fired=False, nr7_score=0.0, is_nr7=False, range_rank=3, breakout_detected=False, breakout_direction='neutral', confidence=0.0, notes='No NR7 pattern detected')",
        "MR11": "MR11Result(protocol_id='MR11', fired=False, squeeze_score=0.0, price_acceleration=-0.0017, volume_surge=1.0746, consecutive_up_days=1, parabolic_move=False, confidence=0.0, notes='No squeeze pattern detected')",
        "MR12": "MR12Result(protocol_id='MR12', fired=False, pump_score=0.0, intraday_move=0.0001, volume_ratio=0.8756, is_pump=False, is_dump=False, confidence=0.0, notes='No pump pattern detected')",
        "MR13": "MR13Result(protocol_id='MR13', fired=False, catalyst_score=0.0, gap_magnitude=0.0, gap_direction='neutral', volume_spike=False, potential_catalyst='none_detected', confidence=0.0, notes='No catalyst pattern detected')",
        "MR14": "MR14Result(protocol_id='MR14', fired=False, fractal_score=0.0, is_new_high=False, is_new_low=False, breakout_strength=0.0, days_since_level=0, confidence=0.0, notes='No fractal breakout detected')",
        "MR15": "MR15Result(protocol_id='MR15', fired=False, extreme_score=0.0, total_return=0.0001, intraday_return=0.0001, is_doubler=False, is_halver=False, confidence=0.0, notes='No extreme move detected')",
        "MR16": "MR16Result(protocol_id='MR16', fired=False, parabolic_score=0.0, five_day_return=-0.0055, acceleration_rate=0.017, is_blow_off=False, exhaustion_risk=0.0, confidence=0.0, notes='No parabolic pattern detected')",
        "MR17": "MR17Result(protocol_id='MR17', fired=False, frenzy_score=0.0, volatility_ratio=0.629, volume_intensity=0.9303, price_swing=0.0312, frenzy_characteristics=0, confidence=0.0, notes='No frenzy pattern detected')",
        "MR18": "MR18Result(protocol_id='MR18', fired=False, gamma_score=0.0, volatility_spike=0.0252, intraday_range_ratio=0.8672, directional_persistence=0.5, gamma_signature=False, confidence=0.0, notes='No gamma ramp detected')",
        "MR19": "MR19Result(protocol_id='MR19', fired=False, fomo_score=0.0, cumulative_return_10d=-0.0197, volume_growth=0.799, consecutive_ups=1, fomo_stage='none', confidence=0.0, notes='No FOMO cascade detected')",
        "MR20": "MR20Result(protocol_id='MR20', fired=False, nuclear_score=0.0, total_return_10d=-0.0197, max_drawdown=0.0208, is_nuclear=False, multiplier=0.9803, confidence=0.0, notes='Minimal pullbacks')"
      }
    },
    "verdict": {
      "action": "structural_weakness",
      "confidence": 0.8349005056353263,
      "primary_signal": "Range-bound structure",
      "risk_factors": [
        "Critical drift from mean"
      ],
      "compliance_note": "Structural analysis only - not trading advice"
    },
    "omega_overrides": {
      "omega_1_safety": false,
      "omega_2_entropy": false,
      "omega_3_drift": true,
      "omega_4_compliance": true
    },
    "proof_hash": "6432a8f0ddf1f1dd738c5e31821be715814e94fcb54718d5adfe68975ac66f6e"
  },
  "context": {
    "seed": 42,
    "run_id": null,
    "sector": null,
    "market_hours": true,
    "compliance_mode": true
  }
}